bytevault/__init__.py
bytevault/database.py
bytevault/main.py
bytevault-0.1.0.dist-info/licenses/LICENSE
bytevault-0.1.0.dist-info/METADATA
bytevault-0.1.0.dist-info/WHEEL
bytevault-0.1.0.dist-info/entry_points.txt
bytevault-0.1.0.dist-info/top_level.txt
bytevault-0.1.0.dist-info/RECORD
