Metadata-Version: 2.4
Name: bytevault
Version: 0.1.0
Summary: CLI based Password Manager with encrypted database storage.
Home-page: https://github.com/cracking-bytes/ByteVault
Author: Bhavika Nagdeo
Author-email: bhavikanagdeo83@gmail.com
License: MIT
Classifier: Programming Language :: Python :: 3
Classifier: Operating System :: OS Independent
Requires-Python: >=3.8
License-File: LICENSE
Requires-Dist: cryptography
Requires-Dist: mysql-connector-python
Dynamic: license-file
